memory_maze/__init__.py
memory_maze/gym_wrappers.py
memory_maze/helpers.py
memory_maze/maze.py
memory_maze/oracle.py
memory_maze/tasks.py
memory_maze/wrappers.py
memory_maze-1.0.3.dist-info/LICENSE
memory_maze-1.0.3.dist-info/METADATA
memory_maze-1.0.3.dist-info/WHEEL
memory_maze-1.0.3.dist-info/top_level.txt
memory_maze-1.0.3.dist-info/RECORD
