Metadata-Version: 2.1
Name: memory-maze
Version: 1.0.3
Summary: Memory Maze is an environment to benchmark memory abilities of RL agents
Home-page: https://github.com/jurgisp/memory-maze
Author: Jurgis Pasukonis
Author-email: jurgisp@gmail.com
Requires-Python: >=3
License-File: LICENSE
Requires-Dist: dm-control
